tencentcloud/__init__.py
tencentcloud/common/__init__.py
tencentcloud/common/credential.py
tcloud_python_sdk-1.0.2.dist-info/LICENSE
tcloud_python_sdk-1.0.2.dist-info/METADATA
tcloud_python_sdk-1.0.2.dist-info/WHEEL
tcloud_python_sdk-1.0.2.dist-info/top_level.txt
tcloud_python_sdk-1.0.2.dist-info/RECORD
